CTFDump.py
CTFDump-0.3.0.dist-info/LICENSE
CTFDump-0.3.0.dist-info/METADATA
CTFDump-0.3.0.dist-info/WHEEL
CTFDump-0.3.0.dist-info/entry_points.txt
CTFDump-0.3.0.dist-info/top_level.txt
CTFDump-0.3.0.dist-info/RECORD
