Metadata-Version: 2.1
Name: CTFDump
Version: 0.3.0
Summary: CTFd Dump - When you want to have an offline copy of a CTF.
Home-page: https://github.com/mosheDO/CTFDump
Author: RealGame (Tomer Zait)
Author-email: realgam3@gmail.com
License: GPLv3
Platform: any
Classifier: License :: OSI Approved :: GNU General Public License v3 (GPLv3)
Classifier: Development Status :: 5 - Production/Stable
Classifier: Environment :: Console
Classifier: Intended Audience :: Science/Research
Classifier: Natural Language :: English
Classifier: Operating System :: MacOS :: MacOS X
Classifier: Operating System :: Microsoft :: Windows
Classifier: Operating System :: POSIX :: Linux
Classifier: Programming Language :: Python :: 3
Classifier: Topic :: Security
Classifier: Topic :: Internet
Classifier: Topic :: Internet :: WWW/HTTP
License-File: LICENSE
Requires-Dist: requests (>=2.24.0)
Requires-Dist: beautifulsoup4 (>=4.9.3)
